tupper/__init__.py
tupper/__main__.py
tupper/console_plotter.py
tupper/constants.py
tupper/export_plotter.py
tupper/solver.py
tupper/string_plotter.py
tupper/test_solver.py
tupper/test_string_plotter.py
tupper-0.10.1.dist-info/LICENSE
tupper-0.10.1.dist-info/METADATA
tupper-0.10.1.dist-info/WHEEL
tupper-0.10.1.dist-info/top_level.txt
tupper-0.10.1.dist-info/RECORD
