Metadata-Version: 2.1
Name: tupper
Version: 0.10.1
Summary: Calculates plots for Tupper's Self-Referential Formula.
Home-page: https://github.com/cariad/py-tupper
Author: Cariad Eccleston
Author-email: cariadeccleston@icloud.com
License: MIT
Platform: UNKNOWN
Classifier: Development Status :: 4 - Beta
Classifier: Environment :: Console
Classifier: Intended Audience :: Developers
Classifier: License :: OSI Approved :: MIT License
Classifier: Natural Language :: English
Classifier: Programming Language :: Python :: 3
Classifier: Operating System :: OS Independent
